seppmail_converter/__init__.py
seppmail_converter/exceptions.py
seppmail_converter/main.py
seppmail_converter-1.2.0.dist-info/LICENSE.md
seppmail_converter-1.2.0.dist-info/METADATA
seppmail_converter-1.2.0.dist-info/WHEEL
seppmail_converter-1.2.0.dist-info/entry_points.txt
seppmail_converter-1.2.0.dist-info/RECORD
