Metadata-Version: 2.1
Name: seppmail-converter
Version: 1.2.0
Summary: Decode SEPPMail emails into EML files
Home-page: https://github.com/mhsp/seppmail-converter
License: AGPL-3.0-or-later
Author: Daniel Malik
Author-email: daniel.malik@mhsp.solutions
Requires-Python: >=3.10,<4.0
Classifier: Environment :: Console
Classifier: License :: OSI Approved :: GNU Affero General Public License v3 or later (AGPLv3+)
Classifier: Programming Language :: Python :: 3
Classifier: Programming Language :: Python :: 3.10
Classifier: Programming Language :: Python :: 3.11
Requires-Dist: beautifulsoup4 (>=4.12.2,<5.0.0)
Requires-Dist: click (>=8.1.6,<9.0.0)
Requires-Dist: lxml (>=4.9.3,<5.0.0)
Requires-Dist: requests (>=2.31,<3.0)
Project-URL: Repository, https://github.com/mhsp/seppmail-converter
